yw_core/__init__.py
yw_core/_version.py
yw_core/builtin_funcs_and_vars.txt
yw_core/cli.py
yw_core/yw_core.py
yw_core-0.1.0.dist-info/licenses/LICENSE
yw_core-0.1.0.dist-info/METADATA
yw_core-0.1.0.dist-info/WHEEL
yw_core-0.1.0.dist-info/entry_points.txt
yw_core-0.1.0.dist-info/top_level.txt
yw_core-0.1.0.dist-info/RECORD
