Metadata-Version: 2.4
Name: yw-core
Version: 0.1.0
Summary: Essential elements of YesWorkflow
Author: Meng Li, Timothy M. McPhillips, Shin-Rong Tsai, Bertram Ludäscher
License-Expression: MIT
Project-URL: Repository, https://github.com/CIRSS/yw-core.git
Keywords: yesworkflow,yw,scientific,provenance,python
Classifier: Development Status :: 3 - Alpha
Classifier: Intended Audience :: Developers
Classifier: Intended Audience :: Science/Research
Classifier: Natural Language :: English
Classifier: Programming Language :: Python :: 3
Requires-Python: >=3.7
License-File: LICENSE
Requires-Dist: nbformat
Requires-Dist: click
Dynamic: license-file
